a2y_testparameters.cp312-win_amd64.pyd
a2y_testparameters-0.8.3.dist-info/LICENSE
a2y_testparameters-0.8.3.dist-info/METADATA
a2y_testparameters-0.8.3.dist-info/WHEEL
a2y_testparameters-0.8.3.dist-info/top_level.txt
a2y_testparameters-0.8.3.dist-info/RECORD
